yuhanboxl/__init__.py
yuhanboxl/ai.py
yuhanboxl/file_manage.py
yuhanboxl/global_functions.py
yuhanboxl/office_functions.py
yuhanboxl-0.3.5.dist-info/licenses/LICENSE
yuhanboxl-0.3.5.dist-info/METADATA
yuhanboxl-0.3.5.dist-info/WHEEL
yuhanboxl-0.3.5.dist-info/top_level.txt
yuhanboxl-0.3.5.dist-info/RECORD
